nonebot_plugin_qqessentials-0.1.4.dist-info/METADATA
nonebot_plugin_qqessentials-0.1.4.dist-info/WHEEL
nonebot_plugin_qqessentials-0.1.4.dist-info/entry_points.txt
nonebot_plugin_qqessentials-0.1.4.dist-info/licenses/LICENSE
nonebot_plugin_qqessentials/__init__.py
nonebot_plugin_qqessentials/__main__.py
nonebot_plugin_qqessentials/config.py
nonebot_plugin_qqessentials/friend.py
nonebot_plugin_qqessentials/funny.py
nonebot_plugin_qqessentials/group.py
nonebot_plugin_qqessentials/help.py
nonebot_plugin_qqessentials/lexicon.py
nonebot_plugin_qqessentials-0.1.4.dist-info/RECORD
