Metadata-Version: 2.1
Name: nonebot-plugin-qqessentials
Version: 0.1.4
Summary: A basic plugin that meets a lot of your needs!
Author-Email: Murasame <congyu@sbhfy.cn>
License: MIT
Project-URL: homepage, https://github.com/Murasame-Dev/nonebot-plugin-qqessentials
Requires-Python: <4.0,>=3.9
Requires-Dist: nonebot2>=2.4.1
Requires-Dist: nonebot-adapter-onebot>=2.4.6
Requires-Dist: httpx>=0.28.1
